EasyMLSelector.py
__init__.py
EasyMLSelector-0.1.0.dist-info/LICENSE
EasyMLSelector-0.1.0.dist-info/METADATA
EasyMLSelector-0.1.0.dist-info/WHEEL
EasyMLSelector-0.1.0.dist-info/top_level.txt
EasyMLSelector-0.1.0.dist-info/RECORD
