Metadata-Version: 2.1
Name: EasyMLSelector
Version: 0.1.0
Summary: Training and Testing for a set of scikit-learn models in one go.
Author-email: wmjg <w.michaelgardner@gmail.com>
Project-URL: Homepage, https://github.com/wmjg-alt/EasyMLSelector
Classifier: Programming Language :: Python :: 3
Classifier: License :: OSI Approved :: MIT License
Classifier: Operating System :: OS Independent
Requires-Python: >=3.7
License-File: LICENSE
